[
  {
    "icon": "book",
    "title": "Digital Resources",
    "description": "Access digital study materials and e-content",
    "url": "https://egyankosh.ac.in/"
  },
  {
    "icon": "headphones",
    "title": "IGNOU Podcast",
    "description": "Listen to educational podcasts",
    "url": "https://freedom2learn.ignouonline.ac.in/pages/"
  },
  {
    "icon": "monitor",
    "title": "WEAS Portal",
    "description": "Web-enabled Academic Support",
    "url": "https://sites.google.com/ignou.ac.in/weas"
  },
  {
    "icon": "book",
    "title": "IGNOU Udyami",
    "description": "Access entrepreneurship resources",
    "url": "https://sites.google.com/ignou.ac.in/ignouudyami"
  },
  {
    "icon": "television",
    "title": "Educational Television",
    "description": "Access educational resources",
    "url": "https://www.ignouonline.ac.in/gyandarshan/"
  }
]